odoo/addons/l10n_br_cnab_structure/README.rst
odoo/addons/l10n_br_cnab_structure/__init__.py
odoo/addons/l10n_br_cnab_structure/__manifest__.py
odoo/addons/l10n_br_cnab_structure/hooks.py
odoo/addons/l10n_br_cnab_structure/cnab/__init__.py
odoo/addons/l10n_br_cnab_structure/cnab/cnab.py
odoo/addons/l10n_br_cnab_structure/data/cnab.line.field.group.csv
odoo/addons/l10n_br_cnab_structure/data/cnab.line.group.field.condition.csv
odoo/addons/l10n_br_cnab_structure/data/cnab.occurrence.csv
odoo/addons/l10n_br_cnab_structure/data/cnab.payment.way.csv
odoo/addons/l10n_br_cnab_structure/data/cnab.pix.key.type.csv
odoo/addons/l10n_br_cnab_structure/data/cnab.pix.transfer.type.csv
odoo/addons/l10n_br_cnab_structure/data/l10n_br_cnab.batch.csv
odoo/addons/l10n_br_cnab_structure/data/l10n_br_cnab.line.csv
odoo/addons/l10n_br_cnab_structure/data/l10n_br_cnab.line.field.csv
odoo/addons/l10n_br_cnab_structure/data/l10n_br_cnab.structure.csv
odoo/addons/l10n_br_cnab_structure/demo/account_account.xml
odoo/addons/l10n_br_cnab_structure/demo/account_invoice.xml
odoo/addons/l10n_br_cnab_structure/demo/account_journal.xml
odoo/addons/l10n_br_cnab_structure/demo/payment_mode.xml
odoo/addons/l10n_br_cnab_structure/demo/res_partner_bank.xml
odoo/addons/l10n_br_cnab_structure/i18n/l10n_br_cnab_structure.pot
odoo/addons/l10n_br_cnab_structure/i18n/pt_BR.po
odoo/addons/l10n_br_cnab_structure/models/__init__.py
odoo/addons/l10n_br_cnab_structure/models/account_journal.py
odoo/addons/l10n_br_cnab_structure/models/account_payment_line.py
odoo/addons/l10n_br_cnab_structure/models/account_payment_mode.py
odoo/addons/l10n_br_cnab_structure/models/account_payment_oder.py
odoo/addons/l10n_br_cnab_structure/models/cnab_batch.py
odoo/addons/l10n_br_cnab_structure/models/cnab_data_management.py
odoo/addons/l10n_br_cnab_structure/models/cnab_line.py
odoo/addons/l10n_br_cnab_structure/models/cnab_line_field.py
odoo/addons/l10n_br_cnab_structure/models/cnab_line_field_group.py
odoo_addon_l10n_br_cnab_structure-16.0.3.0.1.dist-info/METADATA
odoo_addon_l10n_br_cnab_structure-16.0.3.0.1.dist-info/WHEEL
odoo_addon_l10n_br_cnab_structure-16.0.3.0.1.dist-info/top_level.txt
odoo_addon_l10n_br_cnab_structure-16.0.3.0.1.dist-info/RECORD
