Metadata-Version: 2.1
Name: odoo-addon-l10n_br_cnab_structure
Version: 16.0.3.0.1
Requires-Python: >=3.10
Requires-Dist: odoo-addon-l10n_br_account_payment_order>=16.0dev,<16.1dev
Requires-Dist: odoo-addon-l10n_br_coa_generic>=16.0dev,<16.1dev
Requires-Dist: odoo>=16.0a,<16.1dev
Requires-Dist: pyyaml
Requires-Dist: unidecode
Summary: This module allows defining the structure for generating the CNAB file. Used to exchange information with Brazilian banks.
Home-page: https://github.com/OCA/l10n-brazil
License: AGPL-3
Author: Engenere, Escodoo, Odoo Community Association (OCA)
Author-email: support@odoo-community.org
Classifier: Programming Language :: Python
Classifier: Framework :: Odoo
Classifier: Framework :: Odoo :: 16.0
Classifier: License :: OSI Approved :: GNU Affero General Public License v3
